[
    {
        "nid": "Lasso",
        "name": "Lasso",
        "desc": "Pulls units 1 space closer",
        "icon_nid": "Skills",
        "icon_index": [
            3,
            9
        ],
        "components": [
            [
                "min_range",
                1
            ],
            [
                "max_range",
                1
            ],
            [
                "exp",
                11
            ],
            [
                "weapon",
                null
            ],
            [
                "target_enemy",
                null
            ],
            [
                "weapon_type",
                "Light"
            ],
            [
                "status_on_hit",
                "Nothing"
            ],
            [
                "no_double",
                null
            ],
            [
                "draw_back",
                1
            ]
        ]
    }
]